prime_numbers/primo.py
primo_list-1.0.dist-info/LICENSE
primo_list-1.0.dist-info/METADATA
primo_list-1.0.dist-info/WHEEL
primo_list-1.0.dist-info/top_level.txt
primo_list-1.0.dist-info/RECORD
