Metadata-Version: 2.1
Name: primo-list
Version: 1.0
Summary: Prime Number between 0 and N
Home-page: UNKNOWN
Author: Fabricio Araujo
Author-email: fabriap@gmail.com
License: GNU GPLv3
Keywords: Prime numbers
Platform: UNKNOWN
Classifier: Development Status :: 4 - Beta
Classifier: Intended Audience :: Developers
Classifier: Topic :: Utilities
Classifier: License :: OSI Approved :: GNU General Public License v3 (GPLv3)
Classifier: Programming Language :: Python :: 3
Classifier: Operating System :: OS Independent
License-File: LICENSE
